stompy/__init__.py
stompy/filters.py
stompy/harm_decomp.py
stompy/memoize.py
stompy/nanpsd.py
stompy/parse_interval.py
stompy/priority_queue.py
stompy/scriptable.py
stompy/tidal_datum.py
stompy/tide_consts.py
stompy/tide_consts.txt
stompy/undoer.py
stompy/utils.py
stompy/weighted_kde.py
stompy/xr_transect.py
stompy/xr_utils.py
stompy/grid/__init__.py
stompy/grid/cgal_line_walk.py
stompy/grid/cli.py
stompy/grid/depth_connectivity.py
stompy/grid/exact_delaunay.py
stompy/grid/front.py
stompy/grid/geom_types.py
stompy/grid/gmsh_scale_helper.py
stompy/grid/live_dt.py
stompy/grid/merge_ugrid_subgrids.py
stompy/grid/multi_ugrid.py
stompy/grid/optimize_grid.py
stompy/grid/orthogonalize.py
stompy/grid/orthomaker.py
stompy/grid/paver.py
stompy/grid/paver_opt_mixin.py
stompy/grid/quad_grower.py
stompy/grid/quad_laplacian.py
stompy/grid/quad_refine.py
stompy/grid/rebay.py
stompy/grid/sample_to_rectilinear.py
stompy/grid/shadow_cdt.py
stompy/grid/smoother.py
stompy/grid/tom.py
stompy/grid/topojson.py
stompy/grid/triangulate_hole.py
stompy/grid/trigrid.py
stompy/grid/ugrid.py
stompy/grid/unstructured_grid.py
stompy/io/__init__.py
stompy/io/dss.py
stompy/io/landxml.py
stompy/io/match_datasets.py
stompy/io/nmea.py
stompy/io/qnc.py
stompy/io/rbr.py
stompy/io/rdb.py
stompy/io/rdb_codes.py
stompy/io/rdb_datadescriptors.py
stompy/io/rdradcp.py
stompy/io/rdradcp_xr.py
stompy/io/seaduck.py
stompy/io/sontek.py
stompy/io/vtk.py
stompy/io/local/__init__.py
stompy/io/local/asos.py
stompy/io/local/cdec.py
stompy/io/local/cdip_mop.py
stompy/io/local/cimis.py
stompy/io/local/coamps.py
stompy/io/local/common.py
stompy/io/local/hycom.py
stompy/io/local/jodc_mooring.py
stompy/io/local/ndbc.py
stompy/io/local/noaa_coops.py
stompy/io/local/sfsu_wind.py
stompy/io/local/uk_tides.py
stompy/io/local/usgs_nwis.py
stompy/io/local/usgs_sfbay.py
stompy/model/__init__.py
stompy/model/data_comparison.py
stompy/model/dem_to_csgraph.py
stompy/model/dsm2.py
stompy/model/hydro_model.py
stompy_ocean-0.0.5.dist-info/LICENSE
stompy_ocean-0.0.5.dist-info/METADATA
stompy_ocean-0.0.5.dist-info/WHEEL
stompy_ocean-0.0.5.dist-info/top_level.txt
stompy_ocean-0.0.5.dist-info/RECORD
