Metadata-Version: 2.1
Name: stompy-ocean
Version: 0.0.5
Summary: Various python modules related to modeling and oceanographic data analysis.
Home-page: https://github.com/rustychris/stompy
Author: Rusty Holleman
Author-email: Rusty Holleman <rustychris@gmail.com>
License: MIT License
Project-URL: Homepage, https://github.com/rustychris/stompy
Keywords: modeling,oceanography,grid
Classifier: License :: OSI Approved :: MIT License
Classifier: Programming Language :: Python
Classifier: Programming Language :: Python :: 3
Requires-Python: >=3.0
License-File: LICENSE
Requires-Dist: cmocean
Requires-Dist: matplotlib
Requires-Dist: netCDF4
Requires-Dist: pandas
Requires-Dist: requests
Requires-Dist: scipy
Requires-Dist: Shapely
Requires-Dist: six
Requires-Dist: xarray
Requires-Dist: seawater
Requires-Dist: gdal<3.9
Requires-Dist: numpy<2.0
Requires-Dist: cgal
